lyapunov_lab/__init__.py
lyapunov_lab/cli.py
lyapunov_lab/backend/__init__.py
lyapunov_lab/backend/app.py
lyapunov_lab/backend/hello.py
lyapunov_lab-0.1.10.dist-info/licenses/LICENSE
lyapunov_lab-0.1.10.dist-info/METADATA
lyapunov_lab-0.1.10.dist-info/WHEEL
lyapunov_lab-0.1.10.dist-info/entry_points.txt
lyapunov_lab-0.1.10.dist-info/top_level.txt
lyapunov_lab-0.1.10.dist-info/RECORD
