Metadata-Version: 2.4
Name: lyapunov-lab
Version: 0.1.10
Summary: Chaos Analyzer hardware dashboard
Author-email: Your Name <you@example.com>
Requires-Python: >=3.8
License-File: LICENSE
Requires-Dist: fastapi
Requires-Dist: uvicorn
Requires-Dist: pydantic
Requires-Dist: pyserial
Requires-Dist: click
Requires-Dist: python-multipart>=0.0.20
Requires-Dist: bump2version>=1.0.1
Dynamic: license-file
